topsis_ravish/__init__.py
topsis_ravish/topsis.py
topsis_ravish_102303651-0.0.4.dist-info/LICENSE
topsis_ravish_102303651-0.0.4.dist-info/METADATA
topsis_ravish_102303651-0.0.4.dist-info/WHEEL
topsis_ravish_102303651-0.0.4.dist-info/entry_points.txt
topsis_ravish_102303651-0.0.4.dist-info/top_level.txt
topsis_ravish_102303651-0.0.4.dist-info/RECORD
