Metadata-Version: 2.1
Name: topsis-ravish-102303651
Version: 0.0.4
Summary: TOPSIS implementation
Author: ravish
Author-email: sharmaravish77400@gmail.com
License: MIT License
Classifier: License :: OSI Approved :: MIT License
Classifier: Programming Language :: Python :: 3
Classifier: Programming Language :: Python :: 3 :: Only
License-File: LICENSE
Requires-Dist: pandas
Requires-Dist: numpy
